[
  {
    "trades": 351,
    "wr": 45.6,
    "pf": 1.32,
    "pnl": 912193.0,
    "ann": 143.2,
    "dd": 54.0,
    "avg_rr": 1.57,
    "calmar": 2.65,
    "sharpe": 1.05,
    "noise_pct": 2.8,
    "mode": "structure",
    "val": 20,
    "symbol": "LH",
    "label": "Struct20"
  },
  {
    "trades": 351,
    "wr": 44.4,
    "pf": 1.34,
    "pnl": 892993.0,
    "ann": 140.7,
    "dd": 57.5,
    "avg_rr": 1.68,
    "calmar": 2.45,
    "sharpe": 1.15,
    "noise_pct": 3.1,
    "mode": "structure",
    "val": 15,
    "symbol": "LH",
    "label": "Struct15"
  },
  {
    "trades": 351,
    "wr": 43.9,
    "pf": 1.4,
    "pnl": 953233.0,
    "ann": 148.4,
    "dd": 61.9,
    "avg_rr": 1.79,
    "calmar": 2.4,
    "sharpe": 1.3,
    "noise_pct": 3.1,
    "mode": "structure",
    "val": 12,
    "symbol": "LH",
    "label": "Struct12"
  },
  {
    "trades": 351,
    "wr": 45.6,
    "pf": 1.27,
    "pnl": 914587.0,
    "ann": 143.5,
    "dd": 63.9,
    "avg_rr": 1.52,
    "calmar": 2.24,
    "sharpe": 1.05,
    "noise_pct": 0.0,
    "mode": "atr_mult",
    "val": 2.5,
    "symbol": "LH",
    "label": "ATR2.5"
  },
  {
    "trades": 351,
    "wr": 43.0,
    "pf": 1.42,
    "pnl": 936673.0,
    "ann": 146.3,
    "dd": 68.2,
    "avg_rr": 1.88,
    "calmar": 2.14,
    "sharpe": 1.35,
    "noise_pct": 3.1,
    "mode": "structure",
    "val": 10,
    "symbol": "LH",
    "label": "Struct10"
  },
  {
    "trades": 351,
    "wr": 40.5,
    "pf": 1.31,
    "pnl": 845130.0,
    "ann": 134.5,
    "dd": 65.8,
    "avg_rr": 1.93,
    "calmar": 2.05,
    "sharpe": 1.24,
    "noise_pct": 0.0,
    "mode": "atr_mult",
    "val": 1.5,
    "symbol": "LH",
    "label": "ATR1.5"
  },
  {
    "trades": 351,
    "wr": 42.2,
    "pf": 1.41,
    "pnl": 862753.0,
    "ann": 136.8,
    "dd": 73.9,
    "avg_rr": 1.94,
    "calmar": 1.85,
    "sharpe": 1.36,
    "noise_pct": 3.4,
    "mode": "structure",
    "val": 8,
    "symbol": "LH",
    "label": "Struct8"
  },
  {
    "trades": 351,
    "wr": 41.9,
    "pf": 1.26,
    "pnl": 793907.0,
    "ann": 127.8,
    "dd": 73.1,
    "avg_rr": 1.75,
    "calmar": 1.75,
    "sharpe": 1.07,
    "noise_pct": 0.3,
    "mode": "atr_mult",
    "val": 1.8,
    "symbol": "LH",
    "label": "ATR1.8"
  },
  {
    "trades": 351,
    "wr": 42.7,
    "pf": 1.25,
    "pnl": 779187.0,
    "ann": 125.8,
    "dd": 75.0,
    "avg_rr": 1.67,
    "calmar": 1.68,
    "sharpe": 1.01,
    "noise_pct": 0.0,
    "mode": "atr_mult",
    "val": 2.0,
    "symbol": "LH",
    "label": "ATR2.0"
  },
  {
    "trades": 351,
    "wr": 37.9,
    "pf": 1.26,
    "pnl": 659675.0,
    "ann": 109.6,
    "dd": 70.9,
    "avg_rr": 2.07,
    "calmar": 1.54,
    "sharpe": 1.11,
    "noise_pct": 0.0,
    "mode": "atr_mult",
    "val": 1.3,
    "symbol": "LH",
    "label": "ATR1.3"
  },
  {
    "trades": 351,
    "wr": 46.2,
    "pf": 1.19,
    "pnl": 708776.0,
    "ann": 116.3,
    "dd": 79.2,
    "avg_rr": 1.39,
    "calmar": 1.47,
    "sharpe": 0.8,
    "noise_pct": 0.0,
    "mode": "atr_mult",
    "val": 3.0,
    "symbol": "LH",
    "label": "ATR3.0"
  },
  {
    "trades": 351,
    "wr": 39.9,
    "pf": 1.33,
    "pnl": 608353.0,
    "ann": 102.4,
    "dd": 79.9,
    "avg_rr": 2.0,
    "calmar": 1.28,
    "sharpe": 1.18,
    "noise_pct": 5.1,
    "mode": "structure",
    "val": 5,
    "symbol": "LH",
    "label": "Struct5"
  },
  {
    "trades": 351,
    "wr": 41.0,
    "pf": 1.23,
    "pnl": 711204.0,
    "ann": 116.7,
    "dd": 117.1,
    "avg_rr": 1.77,
    "calmar": 1.0,
    "sharpe": 0.98,
    "noise_pct": 0.0,
    "mode": "fixed_points",
    "val": "319.48062",
    "symbol": "LH",
    "label": "Fix319pt"
  },
  {
    "trades": 351,
    "wr": 33.3,
    "pf": 1.16,
    "pnl": 351656.0,
    "ann": 63.8,
    "dd": 102.1,
    "avg_rr": 2.32,
    "calmar": 0.63,
    "sharpe": 0.79,
    "noise_pct": 0.6,
    "mode": "atr_mult",
    "val": 1.0,
    "symbol": "LH",
    "label": "ATR1.0"
  },
  {
    "trades": 351,
    "wr": 29.1,
    "pf": 1.03,
    "pnl": 39833.0,
    "ann": 8.3,
    "dd": 92.5,
    "avg_rr": 2.52,
    "calmar": 0.09,
    "sharpe": 0.19,
    "noise_pct": 8.3,
    "mode": "atr_mult",
    "val": 0.5,
    "symbol": "LH",
    "label": "ATR0.5"
  },
  {
    "trades": 351,
    "wr": 28.5,
    "pf": 0.98,
    "pnl": -34794.0,
    "ann": -7.5,
    "dd": 141.4,
    "avg_rr": 2.47,
    "calmar": -0.05,
    "sharpe": -0.11,
    "noise_pct": 1.4,
    "mode": "fixed_points",
    "val": "159.74031",
    "symbol": "LH",
    "label": "Fix160pt"
  },
  {
    "trades": 351,
    "wr": 27.1,
    "pf": 0.95,
    "pnl": -88935.0,
    "ann": -20.0,
    "dd": 154.3,
    "avg_rr": 2.56,
    "calmar": -0.13,
    "sharpe": -0.34,
    "noise_pct": 3.1,
    "mode": "atr_mult",
    "val": 0.7,
    "symbol": "LH",
    "label": "ATR0.7"
  },
  {
    "trades": 441,
    "wr": 27.7,
    "pf": 0.95,
    "pnl": -96596.0,
    "ann": -17.9,
    "dd": 74.1,
    "avg_rr": 2.49,
    "calmar": -0.24,
    "sharpe": -0.35,
    "noise_pct": 8.4,
    "mode": "fixed_points",
    "val": "18.063135",
    "symbol": "JM",
    "label": "Fix18pt"
  },
  {
    "trades": 441,
    "wr": 49.7,
    "pf": 0.89,
    "pnl": -556795.0,
    "ann": -94.1,
    "dd": 235.7,
    "avg_rr": 0.9,
    "calmar": -0.4,
    "sharpe": -0.7,
    "noise_pct": 0.0,
    "mode": "atr_mult",
    "val": 3.0,
    "symbol": "RM",
    "label": "ATR3.0"
  },
  {
    "trades": 441,
    "wr": 26.8,
    "pf": 0.87,
    "pnl": -321852.0,
    "ann": -54.4,
    "dd": 137.1,
    "avg_rr": 2.37,
    "calmar": -0.4,
    "sharpe": -0.92,
    "noise_pct": 5.4,
    "mode": "fixed_points",
    "val": "31.915731",
    "symbol": "RM",
    "label": "Fix32pt"
  },
  {
    "trades": 351,
    "wr": 26.2,
    "pf": 0.87,
    "pnl": -179358.0,
    "ann": -44.0,
    "dd": 104.5,
    "avg_rr": 2.45,
    "calmar": -0.42,
    "sharpe": -1.03,
    "noise_pct": 6.6,
    "mode": "fixed_points",
    "val": "95.84419",
    "symbol": "LH",
    "label": "Fix96pt"
  },
  {
    "trades": 441,
    "wr": 24.0,
    "pf": 0.74,
    "pnl": -812914.0,
    "ann": -137.4,
    "dd": 320.7,
    "avg_rr": 2.34,
    "calmar": -0.43,
    "sharpe": -1.86,
    "noise_pct": 3.2,
    "mode": "atr_mult",
    "val": 0.7,
    "symbol": "JM",
    "label": "ATR0.7"
  },
  {
    "trades": 441,
    "wr": 26.8,
    "pf": 0.89,
    "pnl": -335834.0,
    "ann": -56.8,
    "dd": 133.3,
    "avg_rr": 2.45,
    "calmar": -0.43,
    "sharpe": -0.7,
    "noise_pct": 2.9,
    "mode": "fixed_points",
    "val": "30.105223",
    "symbol": "JM",
    "label": "Fix30pt"
  },
  {
    "trades": 441,
    "wr": 32.2,
    "pf": 0.83,
    "pnl": -691074.0,
    "ann": -116.8,
    "dd": 265.1,
    "avg_rr": 1.74,
    "calmar": -0.44,
    "sharpe": -1.17,
    "noise_pct": 1.6,
    "mode": "fixed_points",
    "val": "63.831463",
    "symbol": "RM",
    "label": "Fix64pt"
  },
  {
    "trades": 441,
    "wr": 24.0,
    "pf": 0.75,
    "pnl": -589675.0,
    "ann": -99.7,
    "dd": 221.5,
    "avg_rr": 2.36,
    "calmar": -0.45,
    "sharpe": -1.81,
    "noise_pct": 5.9,
    "mode": "atr_mult",
    "val": 0.5,
    "symbol": "JM",
    "label": "ATR0.5"
  },
  {
    "trades": 441,
    "wr": 26.3,
    "pf": 0.81,
    "pnl": -391838.0,
    "ann": -66.2,
    "dd": 143.7,
    "avg_rr": 2.28,
    "calmar": -0.46,
    "sharpe": -1.32,
    "noise_pct": 8.8,
    "mode": "atr_mult",
    "val": 0.5,
    "symbol": "RM",
    "label": "ATR0.5"
  },
  {
    "trades": 441,
    "wr": 29.0,
    "pf": 0.87,
    "pnl": -205159.0,
    "ann": -44.2,
    "dd": 92.8,
    "avg_rr": 2.12,
    "calmar": -0.48,
    "sharpe": -1.2,
    "noise_pct": 12.5,
    "mode": "fixed_points",
    "val": "19.149439",
    "symbol": "RM",
    "label": "Fix19pt"
  },
  {
    "trades": 441,
    "wr": 37.2,
    "pf": 0.92,
    "pnl": -382568.0,
    "ann": -64.7,
    "dd": 130.6,
    "avg_rr": 1.55,
    "calmar": -0.5,
    "sharpe": -0.51,
    "noise_pct": 0.7,
    "mode": "atr_mult",
    "val": 1.5,
    "symbol": "JM",
    "label": "ATR1.5"
  },
  {
    "trades": 441,
    "wr": 36.7,
    "pf": 0.91,
    "pnl": -304729.0,
    "ann": -51.5,
    "dd": 103.7,
    "avg_rr": 1.57,
    "calmar": -0.5,
    "sharpe": -0.49,
    "noise_pct": 3.9,
    "mode": "structure",
    "val": 5,
    "symbol": "JM",
    "label": "Struct5"
  },
  {
    "trades": 441,
    "wr": 33.3,
    "pf": 0.75,
    "pnl": -1063404.0,
    "ann": -179.7,
    "dd": 360.2,
    "avg_rr": 1.5,
    "calmar": -0.5,
    "sharpe": -1.79,
    "noise_pct": 0.7,
    "mode": "atr_mult",
    "val": 1.3,
    "symbol": "RM",
    "label": "ATR1.3"
  },
  {
    "trades": 441,
    "wr": 28.1,
    "pf": 0.76,
    "pnl": -899414.0,
    "ann": -152.0,
    "dd": 290.8,
    "avg_rr": 1.94,
    "calmar": -0.52,
    "sharpe": -1.74,
    "noise_pct": 0.9,
    "mode": "atr_mult",
    "val": 1.0,
    "symbol": "RM",
    "label": "ATR1.0"
  },
  {
    "trades": 441,
    "wr": 46.7,
    "pf": 0.82,
    "pnl": -921138.0,
    "ann": -155.7,
    "dd": 297.4,
    "avg_rr": 0.94,
    "calmar": -0.52,
    "sharpe": -1.2,
    "noise_pct": 0.0,
    "mode": "atr_mult",
    "val": 2.5,
    "symbol": "RM",
    "label": "ATR2.5"
  },
  {
    "trades": 441,
    "wr": 39.5,
    "pf": 0.92,
    "pnl": -325129.0,
    "ann": -55.0,
    "dd": 103.5,
    "avg_rr": 1.41,
    "calmar": -0.53,
    "sharpe": -0.43,
    "noise_pct": 2.7,
    "mode": "structure",
    "val": 10,
    "symbol": "JM",
    "label": "Struct10"
  },
  {
    "trades": 441,
    "wr": 42.0,
    "pf": 0.77,
    "pnl": -1154681.0,
    "ann": -195.2,
    "dd": 359.7,
    "avg_rr": 1.07,
    "calmar": -0.54,
    "sharpe": -1.61,
    "noise_pct": 0.0,
    "mode": "atr_mult",
    "val": 2.0,
    "symbol": "RM",
    "label": "ATR2.0"
  },
  {
    "trades": 441,
    "wr": 38.1,
    "pf": 0.71,
    "pnl": -1478652.0,
    "ann": -249.9,
    "dd": 454.4,
    "avg_rr": 1.15,
    "calmar": -0.55,
    "sharpe": -2.15,
    "noise_pct": 0.7,
    "mode": "atr_mult",
    "val": 1.8,
    "symbol": "RM",
    "label": "ATR1.8"
  },
  {
    "trades": 441,
    "wr": 35.4,
    "pf": 0.71,
    "pnl": -1348852.0,
    "ann": -228.0,
    "dd": 406.6,
    "avg_rr": 1.3,
    "calmar": -0.56,
    "sharpe": -2.14,
    "noise_pct": 0.5,
    "mode": "atr_mult",
    "val": 1.5,
    "symbol": "RM",
    "label": "ATR1.5"
  },
  {
    "trades": 441,
    "wr": 29.7,
    "pf": 0.86,
    "pnl": -578093.0,
    "ann": -97.7,
    "dd": 170.0,
    "avg_rr": 2.02,
    "calmar": -0.57,
    "sharpe": -0.97,
    "noise_pct": 1.8,
    "mode": "atr_mult",
    "val": 1.0,
    "symbol": "JM",
    "label": "ATR1.0"
  },
  {
    "trades": 441,
    "wr": 39.9,
    "pf": 0.92,
    "pnl": -354979.0,
    "ann": -60.0,
    "dd": 104.7,
    "avg_rr": 1.38,
    "calmar": -0.57,
    "sharpe": -0.45,
    "noise_pct": 2.7,
    "mode": "structure",
    "val": 12,
    "symbol": "JM",
    "label": "Struct12"
  },
  {
    "trades": 441,
    "wr": 24.0,
    "pf": 0.76,
    "pnl": -678581.0,
    "ann": -114.7,
    "dd": 187.2,
    "avg_rr": 2.41,
    "calmar": -0.61,
    "sharpe": -1.69,
    "noise_pct": 5.4,
    "mode": "atr_mult",
    "val": 0.7,
    "symbol": "RM",
    "label": "ATR0.7"
  },
  {
    "trades": 441,
    "wr": 44.0,
    "pf": 0.83,
    "pnl": -1011979.0,
    "ann": -171.0,
    "dd": 273.4,
    "avg_rr": 1.06,
    "calmar": -0.63,
    "sharpe": -1.11,
    "noise_pct": 0.0,
    "mode": "atr_mult",
    "val": 3.0,
    "symbol": "JM",
    "label": "ATR3.0"
  },
  {
    "trades": 441,
    "wr": 34.0,
    "pf": 0.85,
    "pnl": -680395.0,
    "ann": -115.0,
    "dd": 179.3,
    "avg_rr": 1.65,
    "calmar": -0.64,
    "sharpe": -1.0,
    "noise_pct": 1.1,
    "mode": "atr_mult",
    "val": 1.3,
    "symbol": "JM",
    "label": "ATR1.3"
  },
  {
    "trades": 441,
    "wr": 38.5,
    "pf": 0.93,
    "pnl": -260779.0,
    "ann": -64.4,
    "dd": 100.4,
    "avg_rr": 1.48,
    "calmar": -0.64,
    "sharpe": -0.54,
    "noise_pct": 2.9,
    "mode": "structure",
    "val": 8,
    "symbol": "JM",
    "label": "Struct8"
  },
  {
    "trades": 441,
    "wr": 34.7,
    "pf": 0.78,
    "pnl": -1135464.0,
    "ann": -191.9,
    "dd": 258.4,
    "avg_rr": 1.46,
    "calmar": -0.74,
    "sharpe": -1.57,
    "noise_pct": 0.7,
    "mode": "fixed_points",
    "val": "60.210445",
    "symbol": "JM",
    "label": "Fix60pt"
  },
  {
    "trades": 441,
    "wr": 38.5,
    "pf": 0.75,
    "pnl": -841281.0,
    "ann": -142.2,
    "dd": 192.1,
    "avg_rr": 1.19,
    "calmar": -0.74,
    "sharpe": -1.63,
    "noise_pct": 2.7,
    "mode": "structure",
    "val": 5,
    "symbol": "RM",
    "label": "Struct5"
  },
  {
    "trades": 441,
    "wr": 41.3,
    "pf": 0.89,
    "pnl": -518179.0,
    "ann": -87.6,
    "dd": 114.1,
    "avg_rr": 1.26,
    "calmar": -0.77,
    "sharpe": -0.63,
    "noise_pct": 2.3,
    "mode": "structure",
    "val": 20,
    "symbol": "JM",
    "label": "Struct20"
  },
  {
    "trades": 441,
    "wr": 44.4,
    "pf": 0.77,
    "pnl": -1053881.0,
    "ann": -178.1,
    "dd": 227.8,
    "avg_rr": 0.96,
    "calmar": -0.78,
    "sharpe": -1.47,
    "noise_pct": 1.6,
    "mode": "structure",
    "val": 20,
    "symbol": "RM",
    "label": "Struct20"
  },
  {
    "trades": 441,
    "wr": 42.4,
    "pf": 0.82,
    "pnl": -1071704.0,
    "ann": -181.1,
    "dd": 223.8,
    "avg_rr": 1.11,
    "calmar": -0.81,
    "sharpe": -1.23,
    "noise_pct": 0.0,
    "mode": "atr_mult",
    "val": 2.5,
    "symbol": "JM",
    "label": "ATR2.5"
  },
  {
    "trades": 441,
    "wr": 42.2,
    "pf": 0.73,
    "pnl": -1144281.0,
    "ann": -193.4,
    "dd": 239.5,
    "avg_rr": 1.01,
    "calmar": -0.81,
    "sharpe": -1.75,
    "noise_pct": 2.5,
    "mode": "structure",
    "val": 12,
    "symbol": "RM",
    "label": "Struct12"
  },
  {
    "trades": 441,
    "wr": 43.8,
    "pf": 0.78,
    "pnl": -971681.0,
    "ann": -164.2,
    "dd": 203.3,
    "avg_rr": 1.0,
    "calmar": -0.81,
    "sharpe": -1.4,
    "noise_pct": 1.8,
    "mode": "structure",
    "val": 15,
    "symbol": "RM",
    "label": "Struct15"
  },
  {
    "trades": 441,
    "wr": 39.7,
    "pf": 0.72,
    "pnl": -1060881.0,
    "ann": -179.3,
    "dd": 219.6,
    "avg_rr": 1.1,
    "calmar": -0.82,
    "sharpe": -1.82,
    "noise_pct": 2.5,
    "mode": "structure",
    "val": 8,
    "symbol": "RM",
    "label": "Struct8"
  },
  {
    "trades": 441,
    "wr": 39.2,
    "pf": 0.84,
    "pnl": -814960.0,
    "ann": -137.7,
    "dd": 166.2,
    "avg_rr": 1.31,
    "calmar": -0.83,
    "sharpe": -1.04,
    "noise_pct": 0.2,
    "mode": "atr_mult",
    "val": 1.8,
    "symbol": "JM",
    "label": "ATR1.8"
  },
  {
    "trades": 441,
    "wr": 41.0,
    "pf": 0.86,
    "pnl": -754150.0,
    "ann": -127.5,
    "dd": 154.0,
    "avg_rr": 1.23,
    "calmar": -0.83,
    "sharpe": -0.92,
    "noise_pct": 0.2,
    "mode": "atr_mult",
    "val": 2.0,
    "symbol": "JM",
    "label": "ATR2.0"
  },
  {
    "trades": 441,
    "wr": 40.6,
    "pf": 0.72,
    "pnl": -1160681.0,
    "ann": -196.2,
    "dd": 235.0,
    "avg_rr": 1.05,
    "calmar": -0.83,
    "sharpe": -1.86,
    "noise_pct": 2.3,
    "mode": "structure",
    "val": 10,
    "symbol": "RM",
    "label": "Struct10"
  },
  {
    "trades": 441,
    "wr": 40.6,
    "pf": 0.85,
    "pnl": -656029.0,
    "ann": -110.9,
    "dd": 120.2,
    "avg_rr": 1.25,
    "calmar": -0.92,
    "sharpe": -0.83,
    "noise_pct": 2.5,
    "mode": "structure",
    "val": 15,
    "symbol": "JM",
    "label": "Struct15"
  }
]